README.txt
setup.py
src/mekk/__init__.py
src/mekk.postrank.egg-info/PKG-INFO
src/mekk.postrank.egg-info/SOURCES.txt
src/mekk.postrank.egg-info/dependency_links.txt
src/mekk.postrank.egg-info/namespace_packages.txt
src/mekk.postrank.egg-info/requires.txt
src/mekk.postrank.egg-info/top_level.txt
src/mekk.postrank.egg-info/zip-safe
src/mekk/postrank/__init__.py
src/mekk/postrank/postrank_client.py