Metadata-Version: 1.0
Name: mekk.postrank
Version: 0.1.0
Summary: Simple wrapper for PostRank API.
Home-page: http://bitbucket.org/Mekk/mekk.postrank
Author: Marcin Kasperski
Author-email: Marcin.Kasperski@mekk.waw.pl
License: BSD
Keywords: org
Platform: UNKNOWN
Classifier: Programming Language :: Python
Classifier: Intended Audience :: Developers
Classifier: Topic :: Software Development :: Libraries :: Python Modules
